zope.minmax-3.0-py3.12-nspkg.pth
zope/minmax/__init__.py
zope/minmax/_minmax.py
zope/minmax/interfaces.py
zope/minmax/tests.py
zope_minmax-3.0.dist-info/licenses/LICENSE.txt
zope_minmax-3.0.dist-info/METADATA
zope_minmax-3.0.dist-info/WHEEL
zope_minmax-3.0.dist-info/namespace_packages.txt
zope_minmax-3.0.dist-info/top_level.txt
zope_minmax-3.0.dist-info/RECORD
